display.v
module display (
    input c1,
    input c2,
    input c3,
    input c4,
    input c5,


    output A,
    output B,
    output C,
    output D,
    output E,
    output F,
    output G
);

assign A = (((~c1)&(~c2)&(~c3)&(~c4)&(~c5))| ((c1)&(c2)&(c3)&(c4)&(c5)) | ((c2)&(c3)&(~c4)&(~c5)) | ((~c1)&(~c2)&(c4)&(c5)) | ((~c1)&(c3)&(~c4)&(c5)) | ((~c1)&(c3)&(c4)&(~c5)) | ((c1)&(c2)&(~c3)&(~c4)) | ((c1)&(~c2)&(c3)&(~c4)) | ((c1)&(~c2)&(~c3)&(c5)) | ((c1)&(~c2)&(c4)&(~c5)) | ((c2)&(~c3)&(c4)&(~c5)) | ((c1)&(~c2)&(c4)&(~c5))));

assign B = ((c2) | ((~c2)&(c3)) | ((~c2)&(~c3)&(~c4)&(c5)) | ((~c2)&(~c3)&(c4)) | ((c1)&(~c2)&(~c3)&(~c4)&(~c5)));

assign C = (((~c2)&(~c4)&(~c5)) | ((~c1)&(~c4)&(~c5)) | ((~c2)&(~c3)&(~c4)&(c5)) | ((~c1)&(~c2)&(~c3)&(c5)) | ((~c1)&(~c2)&(c4)&(~c5)) | ((c1)&(~c2)&(~c3)&(~c4)) | ((c2)&(~c3)&(~c4)&(~c5)) | ((~c1)&(~c2)&(~c4)&(c5)) | ((~c1)&(~c3)&(~c4)&(c5)) | ((~c1)&(~c3)&(c4)&(~c5)) | ((c2)&(c3)&(c4)&(c5)) | ((c1)&(c3)&(c4)&(c5)) | ((c1)&(c2)&(c3)&(c5)) | ((c1)&(c2)&(c3)&(c4)) | ((c1)&(c2)&(c4)&(c5)));

assign D = (((~c1)&(~c2)&(~c3)&(~c4)&(~c5))| ((c1)&(c2)&(c3)&(c4)&(c5)) | ((c2)&(c3)&(~c4)&(~c5)) | ((~c1)&(~c2)&(c4)&(c5)) | ((~c1)&(c3)&(~c4)&(c5)) | ((~c1)&(c3)&(c4)&(~c5)) | ((c1)&(c2)&(~c3)&(~c4)) | ((c1)&(~c2)&(c3)&(~c4)) | ((c1)&(~c2)&(~c3)&(c5)) | ((c1)&(~c2)&(c4)&(~c5)) | ((c2)&(~c3)&(c4)&(~c5)));

assign E = (((~c1)&(c2)&(~c3)&(c4)&(c5)) | ((~c1)&(c2)&(c3)&(~c4)&(c5)) | ((~c1)&(~c2)&(c3)&(c4)&(c5)) | ((~c1)&(c2)&(c3)&(c4)&(~c5)) | ((c1)&(c2)&(c3)&(~c4)&(~c5)) | ((c1)&(c2)&(~c3)&(~c4)&(c5)) | ((c1)&(~c2)&(c3)&(~c4)&(c5)) | ((c1)&(~c2)&(~c3)&(c4)&(c5)) | ((c1)&(c2)&(c3)&(c4)&(c5)) | ((c1)&(~c2)&(c3)&(c4)&(~c5)) | ((c1)&(c2)&(~c3)&(c4)&(~c5)));

assign F = (((~c1)&(c2)&(~c3)&(~c4)&(~c5)) | ((~c1)&(~c2)&(~c4)&(~c5)) | ((~c1)&(~c2)&(~c3)&(~c4)&(c5)) | ((~c1)&(~c2)&(~c3)&(c4)&(~c5)) | ((c1)&(c2)&(c3)&(c4)&(c5)) | ((c1)&(~c2)&(~c3)&(~c4)&(~c5)));
//assign F = (((c1)&(c2)&(c3)&(c4)&(c5)) | ((~c2)&(~c3)&(~c4)&(~c5)) | ((~c1)&(~c2)&(~c3)&(~c4)) | ((~c1)&(~c2)&(~c4)&(~c5)) | ((~c1)&(~c2)&(~c3)&(c5)) | ((~c1)&(~c3)&(~c4)&(~c5)));

assign G = (((~c2)&(~c3)) | ((~c2)&(c3)&(~c4)) | ((~c1)&(c2)&(~c3)) | ((c2)&(~c3)&(~c4)) | ((c2)&(c3)&(~c4)&(~c5)) | ((~c1)&(c2)&(~c4)&(c5)) | ((~c1)&(~c2)&(c4)) | ((c2)&(~c3)&(c4)&(~c5)) | ((~c2)&(c4)&(~c5)) | ((~c1)&(c4)&(~c5)));

endmodule

testebench.v
`include "display.v"

module testbench ();

reg C1 = 0;
reg C2 = 0;
reg C3 = 0;
reg C4 = 1;
reg C5 = 0;

wire A;
wire B;
wire C;
wire D;
wire E;
wire F;
wire G;

display meumoduloTeste(C1,C2,C3,C4,C5,A,B,C,D,E,F,G);

initial begin
    $dumpfile("testbench.vcd");
    $dumpvars;

    #100;
    $finish;
end

endmodule

testbench.vcd
$date
	Thu Mar 25 20:50:37 2021
$end
$version
	Icarus Verilog
$end
$timescale
	1s
$end
$scope module testbench $end
$var wire 1 ! G $end
$var wire 1 " F $end
$var wire 1 # E $end
$var wire 1 $ D $end
$var wire 1 % C $end
$var wire 1 & B $end
$var wire 1 ' A $end
$var reg 1 ( C1 $end
$var reg 1 ) C2 $end
$var reg 1 * C3 $end
$var reg 1 + C4 $end
$var reg 1 , C5 $end
$scope module meumoduloTeste $end
$var wire 1 ' A $end
$var wire 1 & B $end
$var wire 1 % C $end
$var wire 1 $ D $end
$var wire 1 # E $end
$var wire 1 " F $end
$var wire 1 ! G $end
$var wire 1 ( c1 $end
$var wire 1 ) c2 $end
$var wire 1 * c3 $end
$var wire 1 + c4 $end
$var wire 1 , c5 $end
$upscope $end
$upscope $end
$enddefinitions $end
#0
$dumpvars
1,
1+
1*
1)
1(
1'
1&
1%
1$
1#
1"
0!
$end
#1
0#
0'
0$
0"
1&
0)
#2
1!
0%
1'
1$
1#
0,
0*
1)
#3
1%
1!
1'
1$
0#
1,
0+
0(
#4
0$
0'
1"
0,
1+
0)
#5
1%
1'
1$
1"
0&
0+
#6
0$
1&
1,
#7
1$
0"
1+
#8
1%
0$
0'
1"
1&
0,
0+
1*
#9
1$
0"
1,
#10
1'
1$
1%
0,
1+
#11
0%
1#
1,
#12
1%
0$
0'
0#
1"
1!
0,
0+
0*
1)
#13
1'
1$
0"
1+
#14
1#
0%
1,
#15
1%
1$
0#
0,
0+
1*
#16
0%
1#
1,
#17
0,
1+
#18
0'
0$
0#
1%
0!
1,
#19
1!
1%
1"
0,
0+
0*
0)
1(
#20
1$
1'
1&
0"
1,
#21
0%
1'
0,
1+
#22
1#
1,
#23
1%
0#
0$
1'
1&
0,
0+
1*
#24
0%
0'
1$
1#
1,
#25
1'
0,
1+
#26
1%
1'
1$
0#
1!
0+
0*
1)
#27
0%
1#
1,
#28
0$
0#
0!
0'
1%
1+
#29
1#
1!
1'
0%
0,
0+
1*
#30
0#
0!
0'
1$
1%
1,
#31
0$
0,
1+
